<MinutiaeList>
<Minutia X="140" Y="116" Angle="131,0" Type="2"/>
<Minutia X="92" Y="124" Angle="111,0" Type="2"/>
<Minutia X="212" Y="261" Angle="205,0" Type="2"/>
<Minutia X="129" Y="138" Angle="107,0" Type="2"/>
<Minutia X="141" Y="187" Angle="61,0" Type="2"/>
<Minutia X="203" Y="277" Angle="191,0" Type="2"/>
<Minutia X="213" Y="212" Angle="245,00000000000003" Type="2"/>
<Minutia X="178" Y="261" Angle="199,0" Type="2"/>
<Minutia X="202" Y="180" Angle="245,00000000000003" Type="2"/>
<Minutia X="218" Y="243" Angle="221,00000000000003" Type="2"/>
<Minutia X="197" Y="196" Angle="239,0" Type="2"/>
<Minutia X="188" Y="171" Angle="240,99999999999997" Type="2"/>
<Minutia X="85" Y="213" Angle="73,0" Type="2"/>
<Minutia X="205" Y="226" Angle="225,0" Type="2"/>
<Minutia X="243" Y="284" Angle="203,0" Type="2"/>
<Minutia X="228" Y="172" Angle="77,0" Type="2"/>
<Minutia X="165" Y="124" Angle="171,0" Type="2"/>
</MinutiaeList>
