<MinutiaeList Score="3">
<Minutia X="141" Y="161" Angle="345,0" Type="2" />
<Minutia X="178" Y="171" Angle="353,0" Type="2" />
<Minutia X="146" Y="262" Angle="339,0" Type="2" />
<Minutia X="202" Y="197" Angle="357,0" Type="2" />
<Minutia X="253" Y="309" Angle="17,0" Type="2" />
<Minutia X="245" Y="179" Angle="183,0" Type="2" />
<Minutia X="165" Y="330" Angle="149,0" Type="2" />
<Minutia X="203" Y="139" Angle="345,0" Type="2" />
<Minutia X="162" Y="326" Angle="330,99999999999994" Type="2" />
<Minutia X="253" Y="330" Angle="199,0" Type="2" />
<Minutia X="227" Y="252" Angle="5,0" Type="2" />
</MinutiaeList>