<MinutiaeList Score="1">
<Minutia X="228" Y="172" Angle="321,0" Type="2" />
<Minutia X="189" Y="178" Angle="95,0" Type="2" />
<Minutia X="180" Y="211" Angle="89,0" Type="2" />
<Minutia X="259" Y="141" Angle="17,0" Type="2" />
<Minutia X="197" Y="211" Angle="69,00000000000001" Type="2" />
<Minutia X="202" Y="236" Angle="61,0" Type="2" />
<Minutia X="234" Y="267" Angle="203,0" Type="2" />
<Minutia X="252" Y="194" Angle="45,0" Type="2" />
<Minutia X="134" Y="213" Angle="283,0" Type="2" />
<Minutia X="236" Y="187" Angle="77,0" Type="2" />
<Minutia X="177" Y="274" Angle="293,0" Type="2" />
<Minutia X="139" Y="197" Angle="97,0" Type="2" />
<Minutia X="257" Y="260" Angle="213,0" Type="2" />
<Minutia X="213" Y="149" Angle="299,0" Type="2" />
</MinutiaeList>