<MinutiaeList>
  <Minutia X="204" Y="194" Angle="305.6148495720177" Type="2"/>
  <Minutia X="204" Y="229" Angle="143.81536738392336" Type="2"/>
  <Minutia X="148" Y="11" Angle="144.58965118916146" Type="2"/>
  <Minutia X="211" Y="157" Angle="133.661873711106" Type="2"/>
  <Minutia X="165" Y="50" Angle="130.87954174845885" Type="2"/>
  <Minutia X="147" Y="140" Angle="127.78572043582221" Type="2"/>
  <Minutia X="148" Y="108" Angle="302.85148702123485" Type="2"/>
  <Minutia X="171" Y="67" Angle="129.55511591138676" Type="2"/>
  <Minutia X="268" Y="213" Angle="63.747037169789884" Type="2"/>
  <Minutia X="172" Y="115" Angle="143.1284455009705" Type="2"/>
  <Minutia X="325" Y="156" Angle="125.50323292420939" Type="2"/>
  <Minutia X="130" Y="69" Angle="131.36398263574503" Type="2"/>
  <Minutia X="228" Y="181" Angle="305.15669656880965" Type="2"/>
  <Minutia X="173" Y="220" Angle="326.2180009217333" Type="2"/>
  <Minutia X="202" Y="124" Angle="305.259503604852" Type="2"/>
  <Minutia X="243" Y="203" Angle="89.56399253980464" Type="2"/>
  <Minutia X="274" Y="116" Angle="205.55812134974423" Type="2"/>
  <Minutia X="220" Y="203" Angle="131.09436124101885" Type="2"/>
  <Minutia X="180" Y="98" Angle="114.60695587181627" Type="2"/>
</MinutiaeList>
