<MinutiaeList>
  <Minutia X="170" Y="236" Angle="99.31304013397273" Type="2"/>
  <Minutia X="253" Y="212" Angle="89.28063487193508" Type="2"/>
  <Minutia X="227" Y="173" Angle="96.9335778701488" Type="2"/>
  <Minutia X="210" Y="245" Angle="91.46863515229593" Type="2"/>
  <Minutia X="158" Y="138" Angle="129.46985321258538" Type="2"/>
  <Minutia X="181" Y="188" Angle="114.11980642950813" Type="2"/>
  <Minutia X="196" Y="268" Angle="107.75634056419348" Type="2"/>
  <Minutia X="212" Y="195" Angle="278.4353239584757" Type="2"/>
  <Minutia X="155" Y="243" Angle="113.00963000976138" Type="2"/>
  <Minutia X="163" Y="205" Angle="71.80967511203285" Type="2"/>
</MinutiaeList>
